scrapy_testmaster/__init__.py
scrapy_testmaster/cli.py
scrapy_testmaster/config_doc.py
scrapy_testmaster/middleware.py
scrapy_testmaster/parse.py
scrapy_testmaster/utils.py
scrapy_testmaster/utils_novel.py
tests/__init__.py
tests/shared.py
tests/test_middleware.py
tests/test_record.py
tests/test_utils.py
tests/test_validation.py
scrapy_testmaster-1.3.1.dist-info/LICENSE
scrapy_testmaster-1.3.1.dist-info/METADATA
scrapy_testmaster-1.3.1.dist-info/WHEEL
scrapy_testmaster-1.3.1.dist-info/entry_points.txt
scrapy_testmaster-1.3.1.dist-info/top_level.txt
scrapy_testmaster-1.3.1.dist-info/RECORD
