Metadata-Version: 2.1
Name: scrapy-testmaster
Version: 1.3.1
Summary: Automated testing and debugging tool for Scrapy.
Home-page: https://github.com/ThomasAitken/Scrapy-Testmaster
Author: Thomas Aitken
Author-email: tclaitken@gmail.com
License: UNKNOWN
Platform: UNKNOWN
Classifier: Programming Language :: Python :: 3
Classifier: Programming Language :: Python :: 3.6
Classifier: Programming Language :: Python :: 3.7
Classifier: Programming Language :: Python :: 3.8
Classifier: Programming Language :: Python :: 3.9
Classifier: License :: OSI Approved :: BSD License
Classifier: Operating System :: OS Independent
Requires-Dist: datadiff (==2.0.0)
Requires-Dist: requests
